promptstudio/__init__.py
promptstudio/base.py
promptstudio/cli.py
promptstudio/prompt/__init__.py
promptstudio/prompt/cache.py
promptstudio/prompt/types.py
promptstudio/utils/__init__.py
promptstudio/utils/helpers.py
promptstudio_sdk_python-1.0.0.dist-info/LICENSE
promptstudio_sdk_python-1.0.0.dist-info/METADATA
promptstudio_sdk_python-1.0.0.dist-info/WHEEL
promptstudio_sdk_python-1.0.0.dist-info/entry_points.txt
promptstudio_sdk_python-1.0.0.dist-info/top_level.txt
promptstudio_sdk_python-1.0.0.dist-info/RECORD
