Metadata-Version: 2.1
Name: promptstudio-sdk-python
Version: 1.0.0
Summary: Python SDK for PromptStudio
Home-page: https://github.com/promptstudio/promptstudio-python-sdk
Author: PromptStudio
Author-email: support@promptstudio.dev
Project-URL: Bug Tracker, https://github.com/promptstudio/promptstudio-python-sdk/issues
Project-URL: Documentation, https://docs.promptstudio.dev
Project-URL: Source Code, https://github.com/promptstudio/promptstudio-python-sdk
Classifier: Development Status :: 4 - Beta
Classifier: Intended Audience :: Developers
Classifier: License :: OSI Approved :: MIT License
Classifier: Operating System :: OS Independent
Classifier: Programming Language :: Python :: 3
Classifier: Programming Language :: Python :: 3.9
Classifier: Programming Language :: Python :: 3.10
Classifier: Programming Language :: Python :: 3.11
Requires-Python: >=3.9
License-File: LICENSE
Requires-Dist: fastapi>=0.104.0
Requires-Dist: httpx>=0.25.0
Requires-Dist: pydantic>=2.4.2
Requires-Dist: google-generativeai>=0.3.0
Requires-Dist: anthropic>=0.5.0
Requires-Dist: openai>=1.3.0
Requires-Dist: python-jose[cryptography]>=3.3.0
Requires-Dist: diskcache>=5.6.3
Requires-Dist: aiohttp>=3.8.0
Requires-Dist: click>=8.1.0
Provides-Extra: dev
Requires-Dist: pytest>=7.0.0; extra == "dev"
Requires-Dist: pytest-asyncio>=0.21.0; extra == "dev"
Requires-Dist: black>=23.0.0; extra == "dev"
Requires-Dist: isort>=5.12.0; extra == "dev"
Requires-Dist: mypy>=1.0.0; extra == "dev"
Requires-Dist: flake8>=6.0.0; extra == "dev"
Provides-Extra: docs
Requires-Dist: sphinx>=7.0.0; extra == "docs"
Requires-Dist: sphinx-rtd-theme>=1.3.0; extra == "docs"
